{
  "Characters": [
    "Albedo",
    "Alhaitham",
    "Aloy",
    "Amber",
    "AratakiItto",
    "Barbara",
    "Beidou",
    "Bennett",
    "Candace",
    "Chongyun",
    "Collei",
    "Cyno",
    "Dehya",
    "Diluc",
    "Diona",
    "Dori",
    "Eula",
    "Faruzan",
    "Fischl",
    "Ganyu",
    "Gorou",
    "HuTao",
    "Jean",
    "KaedeharaKazuha",
    "Kaeya",
    "KamisatoAyaka",
    "KamisatoAyato",
    "Keqing",
    "Klee",
    "KujouSara",
    "KukiShinobu",
    "Layla",
    "Lisa",
    "Mika",
    "Mona",
    "Nahida",
    "Nilou",
    "Ningguang",
    "Noelle",
    "Qiqi",
    "RaidenShogun",
    "Razor",
    "Rosaria",
    "SangonomiyaKokomi",
    "Sayu",
    "Shenhe",
    "ShikanoinHeizou",
    "Sucrose",
    "Tartaglia",
    "Thoma",
    "Tighnari",
    "Traveler",
    "Venti",
    "Wanderer",
    "Xiangling",
    "Xiao",
    "Xingqiu",
    "Xinyan",
    "YaeMiko",
    "Yanfei",
    "Yaoyao",
    "Yelan",
    "Yoimiya",
    "YunJin",
    "Zhongli"
  ],
  "ArtifactSets": {
    "10001": "ResolutionOfSojourner",
    "10002": "BraveHeart",
    "10003": "DefendersWill",
    "10004": "TinyMiracle",
    "10005": "Berserker",
    "10006": "MartialArtist",
    "10007": "Instructor",
    "10008": "Gambler",
    "10009": "TheExile",
    "10010": "Adventurer",
    "10011": "LuckyDog",
    "10012": "Scholar",
    "10013": "TravelingDoctor",
    "14001": "BlizzardStrayer",
    "14002": "Thundersoother",
    "14003": "Lavawalker",
    "14004": "MaidenBeloved",
    "15001": "GladiatorsFinale",
    "15002": "ViridescentVenerer",
    "15003": "WanderersTroupe",
    "15004": "GlacierAndSnowfield",
    "15005": "ThunderingFury",
    "15006": "CrimsonWitchOfFlames",
    "15007": "NoblesseOblige",
    "15008": "BloodstainedChivalry",
    "15009": "PrayersForIllumination",
    "15010": "PrayersForDestiny",
    "15011": "PrayersForWisdom",
    "15012": "PrayersToTheFirmament",
    "15013": "PrayersToSpringtime",
    "15014": "ArchaicPetra",
    "15015": "RetracingBolide",
    "15016": "HeartOfDepth",
    "15017": "TenacityOfTheMillelith",
    "15018": "PaleFlame",
    "15019": "ShimenawasReminiscence",
    "15020": "EmblemOfSeveredFate",
    "15021": "HuskOfOpulentDreams",
    "15022": "OceanHuedClam",
    "15023": "VermillionHereafter",
    "15024": "EchoesOfAnOffering",
    "15025": "DeepwoodMemories",
    "15026": "GildedDreams",
    "15027": "DesertPavilionChronicle",
    "15028": "FlowerOfParadiseLost"
  },
  "ArtifactSetNames": {
    "ResolutionOfSojourner": "Resolution of Sojourner",
    "BraveHeart": "Brave Heart",
    "DefendersWill": "Defender's Will",
    "TinyMiracle": "Tiny Miracle",
    "Berserker": "Berserker",
    "MartialArtist": "Martial Artist",
    "Instructor": "Instructor",
    "Gambler": "Gambler",
    "TheExile": "The Exile",
    "Adventurer": "Adventurer",
    "LuckyDog": "Lucky Dog",
    "Scholar": "Scholar",
    "TravelingDoctor": "Traveling Doctor",
    "BlizzardStrayer": "Blizzard Strayer",
    "Thundersoother": "Thundersoother",
    "Lavawalker": "Lavawalker",
    "MaidenBeloved": "Maiden Beloved",
    "GladiatorsFinale": "Gladiator's Finale",
    "ViridescentVenerer": "Viridescent Venerer",
    "WanderersTroupe": "Wanderer's Troupe",
    "GlacierAndSnowfield": "Glacier and Snowfield",
    "ThunderingFury": "Thundering Fury",
    "CrimsonWitchOfFlames": "Crimson Witch of Flames",
    "NoblesseOblige": "Noblesse Oblige",
    "BloodstainedChivalry": "Bloodstained Chivalry",
    "PrayersForIllumination": "Prayers for Illumination",
    "PrayersForDestiny": "Prayers for Destiny",
    "PrayersForWisdom": "Prayers for Wisdom",
    "PrayersToTheFirmament": "Prayers to the Firmament",
    "PrayersToSpringtime": "Prayers to Springtime",
    "ArchaicPetra": "Archaic Petra",
    "RetracingBolide": "Retracing Bolide",
    "HeartOfDepth": "Heart of Depth",
    "TenacityOfTheMillelith": "Tenacity of the Millelith",
    "PaleFlame": "Pale Flame",
    "ShimenawasReminiscence": "Shimenawa's Reminiscence",
    "EmblemOfSeveredFate": "Emblem of Severed Fate",
    "HuskOfOpulentDreams": "Husk of Opulent Dreams",
    "OceanHuedClam": "Ocean-Hued Clam",
    "VermillionHereafter": "Vermillion Hereafter",
    "EchoesOfAnOffering": "Echoes of an Offering",
    "DeepwoodMemories": "Deepwood Memories",
    "GildedDreams": "Gilded Dreams",
    "DesertPavilionChronicle": "Desert Pavilion Chronicle",
    "FlowerOfParadiseLost": "Flower of Paradise Lost"
  },
  "WeaponsSword": [
    "AmenomaKageuchi",
    "AquilaFavonia",
    "BlackcliffLongsword",
    "CinnabarSpindle",
    "CoolSteel",
    "DarkIronSword",
    "DullBlade",
    "FavoniusSword",
    "FesteringDesire",
    "FilletBlade",
    "FreedomSworn",
    "HaranGeppakuFutsu",
    "HarbingerOfDawn",
    "IronSting",
    "KagotsurubeIsshin",
    "KeyOfKhajNisut",
    "LightOfFoliarIncision",
    "LionsRoar",
    "MistsplitterReforged",
    "PrimordialJadeCutter",
    "PrizedIsshinBlade",
    "PrototypeRancour",
    "RoyalLongsword",
    "SacrificialSword",
    "SapwoodBlade",
    "SilverSword",
    "SkyriderSword",
    "SkywardBlade",
    "SummitShaper",
    "SwordOfDescension",
    "TheAlleyFlash",
    "TheBlackSword",
    "TheFlute",
    "ToukabouShigure",
    "TravelersHandySword",
    "XiphosMoonlight"
  ],
  "WeaponsClaymore": [
    "Akuoumaru",
    "BeaconOfTheReedSea",
    "BlackcliffSlasher",
    "BloodtaintedGreatsword",
    "DebateClub",
    "FavoniusGreatsword",
    "FerrousShadow",
    "ForestRegalia",
    "KatsuragikiriNagamasa",
    "LithicBlade",
    "LuxuriousSeaLord",
    "MailedFlower",
    "MakhairaAquamarine",
    "OldMercsPal",
    "PrototypeArchaic",
    "Quartz",
    "Rainslasher",
    "RedhornStonethresher",
    "RoyalGreatsword",
    "SacrificialGreatsword",
    "SerpentSpine",
    "SkyriderGreatsword",
    "SkywardPride",
    "SnowTombedStarsilver",
    "SongOfBrokenPines",
    "TheBell",
    "TheUnforged",
    "WasterGreatsword",
    "WhiteIronGreatsword",
    "Whiteblind",
    "WolfsGravestone"
  ],
  "WeaponsPolearm": [
    "BeginnersProtector",
    "BlackTassel",
    "BlackcliffPole",
    "CalamityQueller",
    "CrescentPike",
    "Deathmatch",
    "DragonsBane",
    "DragonspineSpear",
    "EngulfingLightning",
    "FavoniusLance",
    "Halberd",
    "IronPoint",
    "KitainCrossSpear",
    "LithicSpear",
    "MissiveWindspear",
    "Moonpiercer",
    "PrimordialJadeWingedSpear",
    "PrototypeStarglitter",
    "RoyalSpear",
    "SkywardSpine",
    "StaffOfHoma",
    "StaffOfTheScarletSands",
    "TheCatch",
    "VortexVanquisher",
    "WavebreakersFin",
    "WhiteTassel"
  ],
  "WeaponsBow": [
    "AlleyHunter",
    "AmosBow",
    "AquaSimulacra",
    "BlackcliffWarbow",
    "CompoundBow",
    "EbonyBow",
    "ElegyForTheEnd",
    "EndOfTheLine",
    "FadingTwilight",
    "FavoniusWarbow",
    "Hamayumi",
    "HuntersBow",
    "HuntersPath",
    "KingsSquire",
    "Messenger",
    "MitternachtsWaltz",
    "MouunsMoon",
    "PolarStar",
    "Predator",
    "PrototypeCrescent",
    "RavenBow",
    "RecurveBow",
    "RoyalBow",
    "Rust",
    "SacrificialBow",
    "SeasonedHuntersBow",
    "SharpshootersOath",
    "SkywardHarp",
    "Slingshot",
    "TheStringless",
    "TheViridescentHunt",
    "ThunderingPulse",
    "WindblumeOde"
  ],
  "WeaponsCatalyst": [
    "AThousandFloatingDreams",
    "AmberBead",
    "ApprenticesNotes",
    "BlackcliffAgate",
    "DodocoTales",
    "EmeraldOrb",
    "EverlastingMoonglow",
    "EyeOfPerception",
    "FavoniusCodex",
    "Frostbearer",
    "FruitOfFulfillment",
    "HakushinRing",
    "KagurasVerity",
    "LostPrayerToTheSacredWinds",
    "MagicGuide",
    "MappaMare",
    "MemoryOfDust",
    "OathswornEye",
    "OtherworldlyStory",
    "PocketGrimoire",
    "PrototypeAmber",
    "RoyalGrimoire",
    "SacrificialFragments",
    "SkywardAtlas",
    "SolarPearl",
    "TheWidsith",
    "ThrillingTalesOfDragonSlayers",
    "TulaytullahsRemembrance",
    "TwinNephrite",
    "WanderingEvenstar",
    "WineAndSong"
  ]
}